mastools/__init__.py
mastools/models/__init__.py
mastools/models/accounts.py
mastools/models/base.py
mastools/models/users.py
mastools/scripts/cmd_mastools.py
mastools/scripts/common.py
mastools/scripts/unconfirmed_users.py
mastools/scripts/user_changes.py
mastools-0.2.0.dist-info/entry_points.txt
mastools-0.2.0.dist-info/WHEEL
mastools-0.2.0.dist-info/METADATA
mastools-0.2.0.dist-info/RECORD
